rnaglib/__init__.py
rnaglib/algorithms/__init__.py
rnaglib/algorithms/graph_algos.py
rnaglib/algorithms/graphlet_hash.py
rnaglib/algorithms/gvp_algos.py
rnaglib/algorithms/node_sim.py
rnaglib/algorithms/rna_ged_nx.py
rnaglib/bin/__init__.py
rnaglib/bin/rnaglib_download.py
rnaglib/bin/rnaglib_prepare_data.py
rnaglib/config/__init__.py
rnaglib/config/build_iso_mat.py
rnaglib/config/feature_encoders.py
rnaglib/config/generate_modifications_cache.py
rnaglib/config/graph_keys.py
rnaglib/config/ligands.py
rnaglib/config/modifications.py
rnaglib/config/rna_smiles.txt
rnaglib/config/cache/__init__.py
rnaglib/config/cache/modifications_cache.json
rnaglib/data/__init__.py
rnaglib/dataset/__init__.py
rnaglib/dataset/get_statistics.py
rnaglib/dataset/rna.py
rnaglib/dataset/rna_dataset.py
rnaglib/dataset_transforms/DSTransform.py
rnaglib/dataset_transforms/__init__.py
rnaglib/dataset_transforms/cd_hit.py
rnaglib/dataset_transforms/distance_computer.py
rnaglib/dataset_transforms/linear_optimisation.py
rnaglib/dataset_transforms/redundancy_remover.py
rnaglib/dataset_transforms/rna_loader.py
rnaglib/dataset_transforms/similarity_splitter.py
rnaglib/dataset_transforms/splitters.py
rnaglib/dataset_transforms/splitting_utils.py
rnaglib/dataset_transforms/structure_distance_computer.py
rnaglib/drawing/__init__.py
rnaglib/drawing/rna_draw.py
rnaglib/drawing/rna_layout.py
rnaglib/encoders/__init__.py
rnaglib/encoders/encoders.py
rnaglib/examples/__init__.py
rnaglib/examples/rnaglib_first.py
rnaglib/learning/__init__.py
rnaglib/learning/gvp.py
rnaglib/learning/learn.py
rnaglib/learning/learning_utils.py
rnaglib/learning/models.py
rnaglib/learning/task_models.py
rnaglib/prepare_data/__init__.py
rnaglib/prepare_data/chopper.py
rnaglib/prepare_data/fr3d_2_graphs.py
rnaglib/prepare_data/hash_check.py
rnaglib/prepare_data/khop_annotate.py
rnaglib/prepare_data/main.py
rnaglib/prepare_data/retrieve_structures.py
rnaglib/tasks/__init__.py
rnaglib/tasks/task.py
rnaglib/tasks/utils.py
rnaglib-3.4.11.dist-info/licenses/LICENSE
rnaglib-3.4.11.dist-info/METADATA
rnaglib-3.4.11.dist-info/WHEEL
rnaglib-3.4.11.dist-info/entry_points.txt
rnaglib-3.4.11.dist-info/top_level.txt
rnaglib-3.4.11.dist-info/RECORD
