Metadata-Version: 2.4
Name: rnaglib
Version: 3.4.11
Summary: RNAglib: Tools for learning on the structure of RNA using 2.5D geometric representations
Author-email: Vincent Mallet <vincentx15@gmail.com>, Carlos Oliver <oliver@biochem.mpg.de>, Jonathan Broadbent <jonathan.broadbent@mail.utoronto.ca>, "William L. Hamilton" <wlh@cs.mcgill.ca>, Jérome Waldispuhl <jeromew@cs.mcgill.ca>
License: MIT License
Project-URL: Documentation, https://rnaglib.readthedocs.io/en/latest/index.html
Project-URL: GitHub, https://github.com/cgoliver/rnaglib
Keywords: RNA,3D,graph neural network
Requires-Python: >=3.7
License-File: LICENSE
Requires-Dist: biopython
Requires-Dist: dill
Requires-Dist: joblib
Requires-Dist: loguru
Requires-Dist: networkx
Requires-Dist: numpy
Requires-Dist: pydantic
Requires-Dist: rdkit
Requires-Dist: requests
Requires-Dist: scikit-learn
Requires-Dist: seaborn
Requires-Dist: torch
Requires-Dist: torchdata
Requires-Dist: tqdm
Requires-Dist: gemmi
Requires-Dist: bidict
Requires-Dist: rna-fm
Requires-Dist: forgi
Requires-Dist: pulp
Dynamic: license-file
